{"trial_id": "0000", "hyperparameters": {"space": [{"class_name": "Float", "config": {"name": "dropout_rate", "default": 0.1, "conditions": [], "min_value": 0.1, "max_value": 0.8, "step": null, "sampling": null}}, {"class_name": "Float", "config": {"name": "learning_rate", "default": 0.001, "conditions": [], "min_value": 0.001, "max_value": 0.01, "step": null, "sampling": "log"}}, {"class_name": "Choice", "config": {"name": "regulizer", "default": "None", "conditions": [], "values": ["None", "l1", "l2", "l1_l2"], "ordered": false}}], "values": {"dropout_rate": 0.544353926440883, "learning_rate": 0.00782851596704437, "regulizer": "l1_l2", "tuner/epochs": 2, "tuner/initial_epoch": 0, "tuner/bracket": 0, "tuner/round": 0}}, "metrics": {"metrics": {"loss": {"direction": "min", "observations": [{"value": [0.47147512435913086], "step": 0}]}, "val_loss": {"direction": "min", "observations": [{"value": [0.08969259262084961], "step": 0}]}}}, "score": 0.08969259262084961, "best_step": 0, "status": "COMPLETED"}